umigap/__init__.py
"umigap/__init__.py,cover"
umigap/blender.py
"umigap/blender.py,cover"
umigap/cli.py
"umigap/cli.py,cover"
umigap/core.py
"umigap/core.py,cover"
umigap/core_test.py
"umigap/core_test.py,cover"
umigap/umigap_test.py
"umigap/umigap_test.py,cover"
umigap/utils.py
"umigap/utils.py,cover"
umigap/utils_test.py
"umigap/utils_test.py,cover"
umigap-0.1.2.dist-info/entry_points.txt
umigap-0.1.2.dist-info/WHEEL
umigap-0.1.2.dist-info/METADATA
umigap-0.1.2.dist-info/RECORD
